flask_auth_mgr.py
Flask_AuthMgr-2.0.0.dist-info/AUTHORS
Flask_AuthMgr-2.0.0.dist-info/LICENSE
Flask_AuthMgr-2.0.0.dist-info/METADATA
Flask_AuthMgr-2.0.0.dist-info/WHEEL
Flask_AuthMgr-2.0.0.dist-info/top_level.txt
Flask_AuthMgr-2.0.0.dist-info/RECORD
