Metadata-Version: 2.1
Name: Flask-AuthMgr
Version: 2.0.0
Summary: A flask extension based on Flask-HTTPAuth for managing restful API Auth.
Home-page: https://gitee.com/dzlua/Flask-AuthMgr.git
Author: dzlua
Author-email: 505544956@qq.com
License: MIT
Keywords: Flask,Flask-AuthMgr,Flask-HTTPAuth,flask_httpauth,auth,flask_auth_mgr
Platform: any
Classifier: Environment :: Web Environment
Classifier: Intended Audience :: Developers
Classifier: License :: OSI Approved :: MIT License
Classifier: Operating System :: OS Independent
Classifier: Programming Language :: Python
Classifier: Programming Language :: Python :: 2
Classifier: Programming Language :: Python :: 3
Classifier: Topic :: Internet :: WWW/HTTP :: Dynamic Content
Classifier: Topic :: Software Development :: Libraries :: Python Modules
Requires-Dist: Flask-HTTPAuth
